local_wake-0.1.0.dist-info/licenses/LICENSE
lwake/__init__.py
lwake/cli.py
lwake/compare.py
lwake/features.py
lwake/listen.py
lwake/record.py
lwake/models/speech-embedding.onnx
local_wake-0.1.0.dist-info/METADATA
local_wake-0.1.0.dist-info/WHEEL
local_wake-0.1.0.dist-info/entry_points.txt
local_wake-0.1.0.dist-info/top_level.txt
local_wake-0.1.0.dist-info/RECORD
