Metadata-Version: 2.4
Name: local-wake
Version: 0.1.0
Summary: Lightweight local wake word detection that recognizes phrases with just a few user-provided recordings. No model training required.
Author-email: Stanislau Matskevich <st.matskevich@gmail.com>
License-Expression: MIT
Project-URL: Repository, https://github.com/st-matskevich/local-wake
Classifier: Programming Language :: Python :: 3
Classifier: Intended Audience :: Developers
Classifier: Operating System :: OS Independent
Classifier: Topic :: Multimedia :: Sound/Audio :: Speech
Requires-Python: >=3.9
License-File: LICENSE
Requires-Dist: onnxruntime
Requires-Dist: silero-vad
Requires-Dist: librosa
Requires-Dist: sounddevice
Requires-Dist: soundfile
Requires-Dist: numpy
Dynamic: license-file
